mrms_time_series/.DS_Store
mrms_time_series/.ipynb_checkpoints/__init__-checkpoint.py
mrms_time_series/__init__-Copy1.py
mrms_time_series/__init__.py
mrms_time_series-0.1.1.dist-info/LICENSE
mrms_time_series-0.1.1.dist-info/METADATA
mrms_time_series-0.1.1.dist-info/WHEEL
mrms_time_series-0.1.1.dist-info/RECORD
