Metadata-Version: 2.3
Name: mrms-time-series
Version: 0.1.1
Summary: Time Series Downloader for MRMS Products
Author: Gonzalo Forero Buitrago
Author-email: gonzaloforero57@gmail.com
Requires-Python: >=3.11,<4.0
Classifier: Programming Language :: Python :: 3
Classifier: Programming Language :: Python :: 3.11
Classifier: Programming Language :: Python :: 3.12
Classifier: Programming Language :: Python :: 3.13
Requires-Dist: numpy (==1.24.3)
Requires-Dist: plotly (==5.21.0)
Requires-Dist: psutil (==6.0.0)
Requires-Dist: requests (==2.32.3)
